[
    {
        "Name": "Angular habijabi",
        "Description": "Angular habijabi ajasdh asuidh asudh asadh  ashd sadh asidh sd",
        "Price": 200,
        "PictureUrl": "images/products/img1.jpg",
        "ProdctTypeId": 1, 
        "ProdctBrandId": 1
    },
    {
        "Name": "React habijabi",
        "Description": "React habijabi ajasdh asuidh asudh asadh  ashd sadh asidh sd",
        "Price": 400,
        "PictureUrl": "images/products/img3.jpg",
        "ProdctTypeId": 2, 
        "ProdctBrandId": 2
    }
]